[
  {
    "excerpt": "Connect an external site to your WordPress on a Subpath",
    "href": "https://www.sitebay.org/docs/guides/connect-an-external-site-to-wordpress/",
    "lastModified": "2024-04-04T00:00:00Z",
    "linkTitle": "External Sites on a Subpath on WordPress",
    "publishDate": "2024-04-04T00:00:00Z",
    "thumbnail": "https://www.sitebay.org/docs/guides/connect-an-external-site-to-wordpress/ExternalPaths_hu4779046371811308819.jpg",
    "title": "External Sites on a Subpath on WordPress"
  }
]